llama_index/vector_stores/oracledb/__init__.py
llama_index/vector_stores/oracledb/base.py
llama_index_vector_stores_oracledb-0.3.2.dist-info/METADATA
llama_index_vector_stores_oracledb-0.3.2.dist-info/WHEEL
llama_index_vector_stores_oracledb-0.3.2.dist-info/licenses/LICENSE
llama_index_vector_stores_oracledb-0.3.2.dist-info/RECORD
