Metadata-Version: 2.4
Name: llama-index-vector-stores-oracledb
Version: 0.3.2
Summary: llama-index vector_stores oracle database integration
Author-email: Your Name <you@example.com>
License-Expression: MIT
License-File: LICENSE
Requires-Python: <3.13,>=3.9
Requires-Dist: llama-index-core<0.15,>=0.13.0
Requires-Dist: oracledb>=2.2
